[
{
    "model": "products.dress",
    "pk": 1,
    "fields": {
        "name": "Youthful Elegance",
        "description": "cute red dress",
        "cost": "5999",
        "color": "red",
        "length": "mini",
        "material": "flax",
        "photo": "products_images/dress1.jpeg",
        "photo_hover": "products_images/dress1.1.png",
        "category": 4,
        "model": "fitted"
    }
},
{
    "model": "products.dress",
    "pk": 2,
    "fields": {
        "name": "Trendy Twirl",
        "description": "black dress",
        "cost": "4999",
        "color": "black",
        "length": "mini",
        "material": "synthetics",
        "photo": "products_images/dress2.jpg",
        "photo_hover": "products_images/dress2.1.png",
        "category": 1,
        "model": "jacket dress"
    }
},
{
    "model": "products.dress",
    "pk": 3,
    "fields": {
        "name": "Fashionista Flair",
        "description": "fashionable red dress",
        "cost": "5499",
        "color": "red",
        "length": "mini",
        "material": "synthetics",
        "photo": "products_images/dress47.jpeg",
        "photo_hover": "products_images/dress47.1.JPG",
        "category": 2,
        "model": "fitted"
    }
},
{
    "model": "products.dress",
    "pk": 4,
    "fields": {
        "name": "Classic Chic",
        "description": "black dress",
        "cost": "3999",
        "color": "black",
        "length": "mini",
        "material": "flax",
        "photo": "products_images/dress4.jpg",
        "photo_hover": "products_images/dress4.1.png",
        "category": 2,
        "model": "fitted"
    }
},
{
    "model": "products.dress",
    "pk": 5,
    "fields": {
        "name": "Red Wings",
        "description": "unique red dress",
        "cost": "4599",
        "color": "red",
        "length": "mini",
        "material": "synthetics",
        "photo": "products_images/dress5.jpg",
        "photo_hover": "products_images/dress5.1.png",
        "category": 3,
        "model": "semi-fitted"
    }
},
{
    "model": "products.dress",
    "pk": 6,
    "fields": {
        "name": "Modern Muse",
        "description": "black dress",
        "cost": "4299",
        "color": "black",
        "length": "mini",
        "material": "flax",
        "photo": "products_images/dress6.jpg",
        "photo_hover": "products_images/dress6.1.png",
        "category": 4,
        "model": "fitted"
    }
},
{
    "model": "products.dress",
    "pk": 7,
    "fields": {
        "name": "Street Style Chic",
        "description": "red dress",
        "cost": "399",
        "color": "red",
        "length": "mini",
        "material": "synthetics",
        "photo": "products_images/dress7.jpg",
        "photo_hover": "products_images/dress7.1.png",
        "category": 4,
        "model": "fitted"
    }
},
{
    "model": "products.dress",
    "pk": 8,
    "fields": {
        "name": "Vintage Vixen",
        "description": "black dress",
        "cost": "9999",
        "color": "black",
        "length": "midi",
        "material": "flax",
        "photo": "products_images/dress8.png",
        "photo_hover": "products_images/dress8.1.JPG",
        "category": 1,
        "model": "loose"
    }
},
{
    "model": "products.dress",
    "pk": 9,
    "fields": {
        "name": "Couture Queen",
        "description": "black dress",
        "cost": "3999",
        "color": "black",
        "length": "midi",
        "material": "cotton",
        "photo": "products_images/dress9.jpeg",
        "photo_hover": "products_images/dress9.1.png",
        "category": 1,
        "model": "costume"
    }
},
{
    "model": "products.dress",
    "pk": 10,
    "fields": {
        "name": "Daring Diva",
        "description": "grey dress",
        "cost": "4999",
        "color": "grey",
        "length": "mini",
        "material": "synthetics",
        "photo": "products_images/dress10.jpeg",
        "photo_hover": "products_images/dress10.1.png",
        "category": 1,
        "model": "jacket dress"
    }
},
{
    "model": "products.dress",
    "pk": 11,
    "fields": {
        "name": "Sassy Style",
        "description": "grey dress",
        "cost": "3599",
        "color": "grey",
        "length": "mini",
        "material": "synthetics",
        "photo": "products_images/dress11.jpeg",
        "photo_hover": "products_images/dress11.1.png",
        "category": 1,
        "model": "jacket dress"
    }
},
{
    "model": "products.dress",
    "pk": 12,
    "fields": {
        "name": "Edgy Elegance",
        "description": "blue dress",
        "cost": "2999",
        "color": "blue",
        "length": "mini",
        "material": "synthetics",
        "photo": "products_images/dress12.jpeg",
        "photo_hover": "products_images/dress12.1.png",
        "category": 1,
        "model": "jacket dress"
    }
},
{
    "model": "products.dress",
    "pk": 13,
    "fields": {
        "name": "Twilight Twirl",
        "description": "red dress",
        "cost": "3299",
        "color": "red",
        "length": "maxi",
        "material": "cotton",
        "photo": "products_images/dress13.jpeg",
        "photo_hover": "products_images/dress13.1.JPG",
        "category": 3,
        "model": "fitted"
    }
},
{
    "model": "products.dress",
    "pk": 14,
    "fields": {
        "name": "Urban Chic",
        "description": "black dress",
        "cost": "5999",
        "color": "black",
        "length": "mini",
        "material": "flax",
        "photo": "products_images/dress14.jpeg",
        "photo_hover": "products_images/dress14.1.png",
        "category": 1,
        "model": "semi-fitted"
    }
},
{
    "model": "products.dress",
    "pk": 15,
    "fields": {
        "name": "Playful Pleats",
        "description": "Black dress",
        "cost": "2599",
        "color": "black",
        "length": "mini",
        "material": "flax",
        "photo": "products_images/dress15.jpeg",
        "photo_hover": "products_images/dress15.1.png",
        "category": 1,
        "model": "semi-fitted"
    }
},
{
    "model": "products.dress",
    "pk": 16,
    "fields": {
        "name": "Dreamy Drape",
        "description": "Blue dress",
        "cost": "5599",
        "color": "blue",
        "length": "midi",
        "material": "cotton",
        "photo": "products_images/dress16.JPG",
        "photo_hover": "products_images/dress16.1.JPG",
        "category": 2,
        "model": "loose"
    }
},
{
    "model": "products.dress",
    "pk": 17,
    "fields": {
        "name": "Blossom Beauty",
        "description": "yellow dress",
        "cost": "4999",
        "color": "yellow",
        "length": "mini",
        "material": "flax",
        "photo": "products_images/dress17.jpeg",
        "photo_hover": "products_images/dress17.1.JPG",
        "category": 1,
        "model": "semi-fitted"
    }
},
{
    "model": "products.dress",
    "pk": 18,
    "fields": {
        "name": "Vintage Vibe",
        "description": "yellow dress",
        "cost": "3999",
        "color": "yellow",
        "length": "mini",
        "material": "synthetics",
        "photo": "products_images/dress18.jpeg",
        "photo_hover": "products_images/dress18.1.png",
        "category": 2,
        "model": "loose"
    }
},
{
    "model": "products.dress",
    "pk": 19,
    "fields": {
        "name": "Chic Charm",
        "description": "beige dress",
        "cost": "3599",
        "color": "beige",
        "length": "mini",
        "material": "synthetics",
        "photo": "products_images/dress19.jpeg",
        "photo_hover": "products_images/dress19.1.JPG",
        "category": 2,
        "model": "loose"
    }
},
{
    "model": "products.dress",
    "pk": 20,
    "fields": {
        "name": "Dazzling Demeanor",
        "description": "yellow dress",
        "cost": "6599",
        "color": "yellow",
        "length": "mini",
        "material": "flax",
        "photo": "products_images/dress20.jpeg",
        "photo_hover": "products_images/dress20.1.JPG",
        "category": 2,
        "model": "loose"
    }
},
{
    "model": "products.dress",
    "pk": 21,
    "fields": {
        "name": "Sleek Sophistication",
        "description": "blue dress",
        "cost": "13999",
        "color": "blue",
        "length": "mini",
        "material": "cotton",
        "photo": "products_images/dress21.jpeg",
        "photo_hover": "products_images/dress21.1.JPG",
        "category": 1,
        "model": "costume"
    }
},
{
    "model": "products.dress",
    "pk": 22,
    "fields": {
        "name": "Ethereal Elegance",
        "description": "grey dress",
        "cost": "4899",
        "color": "grey",
        "length": "mini",
        "material": "flax",
        "photo": "products_images/dress22.jpeg",
        "photo_hover": "products_images/dress22.1.jpeg",
        "category": 1,
        "model": "semi-fitted"
    }
},
{
    "model": "products.dress",
    "pk": 23,
    "fields": {
        "name": "Kaleid Couture",
        "description": "beige dress",
        "cost": "3599",
        "color": "beige",
        "length": "mini",
        "material": "cotton",
        "photo": "products_images/dress23.jpeg",
        "photo_hover": "products_images/dress23.1.jpeg",
        "category": 1,
        "model": "loose"
    }
},
{
    "model": "products.dress",
    "pk": 24,
    "fields": {
        "name": "Radiant Reverie",
        "description": "white dress",
        "cost": "4999",
        "color": "white",
        "length": "mini",
        "material": "synthetics",
        "photo": "products_images/dress24.jpeg",
        "photo_hover": "<contextlib.nullcontext object at 0x10c8f4bd0>",
        "category": 1,
        "model": "semi-fitted"
    }
},
{
    "model": "products.dress",
    "pk": 25,
    "fields": {
        "name": "Illusion Infusion",
        "description": "multicolored dress",
        "cost": "3499",
        "color": "multicolored",
        "length": "mini",
        "material": "cotton",
        "photo": "products_images/dress25.jpeg",
        "photo_hover": "products_images/dress25.1.jpeg",
        "category": 2,
        "model": "fitted"
    }
},
{
    "model": "products.dress",
    "pk": 26,
    "fields": {
        "name": "Artful Asymmetry",
        "description": "black dress",
        "cost": "7999",
        "color": "black",
        "length": "mini",
        "material": "flax",
        "photo": "products_images/dress26.jpeg",
        "photo_hover": "products_images/dress26.1.png",
        "category": 3,
        "model": "fitted"
    }
},
{
    "model": "products.dress",
    "pk": 27,
    "fields": {
        "name": "Ruffled Romance",
        "description": "black dress",
        "cost": "5999",
        "color": "black",
        "length": "midi",
        "material": "cotton",
        "photo": "products_images/dress27.jpeg",
        "photo_hover": "products_images/dress27.1.JPG",
        "category": 3,
        "model": "fitted"
    }
},
{
    "model": "products.dress",
    "pk": 28,
    "fields": {
        "name": "Belle of the Ball",
        "description": "black dress",
        "cost": "4599",
        "color": "black",
        "length": "mini",
        "material": "synthetics",
        "photo": "products_images/dress28.jpeg",
        "photo_hover": "products_images/dress28.1.JPG",
        "category": 3,
        "model": "fitted"
    }
},
{
    "model": "products.dress",
    "pk": 29,
    "fields": {
        "name": "Floral Fantasy",
        "description": "black dress",
        "cost": "5699",
        "color": "black",
        "length": "mini",
        "material": "synthetics",
        "photo": "products_images/dress29.jpeg",
        "photo_hover": "products_images/dress29.1.png",
        "category": 3,
        "model": "fitted"
    }
},
{
    "model": "products.dress",
    "pk": 30,
    "fields": {
        "name": "Mod Moxie",
        "description": "grey dress",
        "cost": "3999",
        "color": "grey",
        "length": "mini",
        "material": "cotton",
        "photo": "products_images/dress30.jpeg",
        "photo_hover": "products_images/dress30.1.png",
        "category": 2,
        "model": "semi-fitted"
    }
},
{
    "model": "products.dress",
    "pk": 31,
    "fields": {
        "name": "Daring Debut",
        "description": "beige dress",
        "cost": "4599",
        "color": "beige",
        "length": "mini",
        "material": "cotton",
        "photo": "products_images/dress31.jpeg",
        "photo_hover": "products_images/dress31.1.png",
        "category": 1,
        "model": "loose"
    }
},
{
    "model": "products.dress",
    "pk": 32,
    "fields": {
        "name": "Style Savvy",
        "description": "blue dress",
        "cost": "2999",
        "color": "blue",
        "length": "mini",
        "material": "synthetics",
        "photo": "products_images/dress32.jpeg",
        "photo_hover": "products_images/dress32.1.png",
        "category": 1,
        "model": "costume"
    }
},
{
    "model": "products.dress",
    "pk": 33,
    "fields": {
        "name": "Spring Fling",
        "description": "black dress",
        "cost": "9999",
        "color": "black",
        "length": "mini",
        "material": "cotton",
        "photo": "products_images/dress33.jpeg",
        "photo_hover": "products_images/dress33.1.JPG",
        "category": 1,
        "model": "semi-fitted"
    }
},
{
    "model": "products.dress",
    "pk": 34,
    "fields": {
        "name": "Golden Gala",
        "description": "black dress",
        "cost": "8999",
        "color": "black",
        "length": "mini",
        "material": "synthetics",
        "photo": "products_images/dress34.jpeg",
        "photo_hover": "products_images/dress34.1.JPG",
        "category": 1,
        "model": "costume"
    }
},
{
    "model": "products.dress",
    "pk": 35,
    "fields": {
        "name": "Sun-kissed Siren",
        "description": "pink dress",
        "cost": "3899",
        "color": "pink",
        "length": "mini",
        "material": "flax",
        "photo": "products_images/dress35.jpeg",
        "photo_hover": "products_images/dress35.1.jpeg",
        "category": 3,
        "model": "semi-fitted"
    }
},
{
    "model": "products.dress",
    "pk": 36,
    "fields": {
        "name": "Crystal Cascade",
        "description": "black dress",
        "cost": "4599",
        "color": "black",
        "length": "midi",
        "material": "synthetics",
        "photo": "products_images/dress36.jpeg",
        "photo_hover": "products_images/dress36.1.jpeg",
        "category": 2,
        "model": "fitted"
    }
},
{
    "model": "products.dress",
    "pk": 37,
    "fields": {
        "name": "Modern Mirage",
        "description": "grey dress",
        "cost": "2999",
        "color": "grey",
        "length": "maxi",
        "material": "synthetics",
        "photo": "products_images/dress37.jpeg",
        "photo_hover": "products_images/dress37.1.png",
        "category": 3,
        "model": "costume"
    }
},
{
    "model": "products.dress",
    "pk": 38,
    "fields": {
        "name": "Modern Seastorm",
        "description": "grey dress",
        "cost": "4999",
        "color": "grey",
        "length": "mini",
        "material": "cotton",
        "photo": "products_images/dress38.jpeg",
        "photo_hover": "products_images/dress38.1.jpeg",
        "category": 1,
        "model": "fitted"
    }
},
{
    "model": "products.dress",
    "pk": 39,
    "fields": {
        "name": "Celestial Chic",
        "description": "grey dress",
        "cost": "5799",
        "color": "grey",
        "length": "maxi",
        "material": "synthetics",
        "photo": "products_images/dress39.jpeg",
        "photo_hover": "products_images/dress39.1.png",
        "category": 3,
        "model": "costume"
    }
},
{
    "model": "products.dress",
    "pk": 40,
    "fields": {
        "name": "Aurora Amore",
        "description": "pink dress",
        "cost": "7999",
        "color": "pink",
        "length": "mini",
        "material": "synthetics",
        "photo": "products_images/dress40.jpeg",
        "photo_hover": "products_images/dress40.1.jpeg",
        "category": 1,
        "model": "costume"
    }
},
{
    "model": "products.dress",
    "pk": 41,
    "fields": {
        "name": "Prism Perfection",
        "description": "grey dress",
        "cost": "4999",
        "color": "grey",
        "length": "mini",
        "material": "cotton",
        "photo": "products_images/dress41.jpeg",
        "photo_hover": "products_images/dress41.1.png",
        "category": 2,
        "model": "loose"
    }
},
{
    "model": "products.dress",
    "pk": 42,
    "fields": {
        "name": "Fusion Finesse",
        "description": "white dress",
        "cost": "5999",
        "color": "white",
        "length": "midi",
        "material": "cotton",
        "photo": "products_images/dress42.jpeg",
        "photo_hover": "products_images/dress42.1.JPG",
        "category": 2,
        "model": "loose"
    }
},
{
    "model": "products.dress",
    "pk": 43,
    "fields": {
        "name": "Jungle Jive",
        "description": "black dress",
        "cost": "3999",
        "color": "black",
        "length": "midi",
        "material": "flax",
        "photo": "products_images/dress43.jpeg",
        "photo_hover": "products_images/dress43.1.png",
        "category": 1,
        "model": "loose"
    }
},
{
    "model": "products.dress",
    "pk": 44,
    "fields": {
        "name": "Cosmic Couture",
        "description": "black dress",
        "cost": "2999",
        "color": "black",
        "length": "mini",
        "material": "cotton",
        "photo": "products_images/dress44.jpeg",
        "photo_hover": "products_images/dress44.1.JPG",
        "category": 1,
        "model": "semi-fitted"
    }
},
{
    "model": "products.dress",
    "pk": 45,
    "fields": {
        "name": "Coral Cascade",
        "description": "white dress",
        "cost": "4999",
        "color": "white",
        "length": "mini",
        "material": "flax",
        "photo": "products_images/dress45.png",
        "photo_hover": "products_images/dress45.1.JPG",
        "category": 1,
        "model": "semi-fitted"
    }
},
{
    "model": "products.dress",
    "pk": 46,
    "fields": {
        "name": "Lavender Luxe",
        "description": "grey dress",
        "cost": "6999",
        "color": "grey",
        "length": "mini",
        "material": "flax",
        "photo": "products_images/dress46.jpg",
        "photo_hover": "products_images/dress46.1.png",
        "category": 1,
        "model": "semi-fitted"
    }
},
{
    "model": "products.dress",
    "pk": 47,
    "fields": {
        "name": "Enchanted Elegance",
        "description": "red dress",
        "cost": "5999",
        "color": "red",
        "length": "mini",
        "material": "synthetics",
        "photo": "products_images/dress3.JPG",
        "photo_hover": "products_images/dress3.1.JPG",
        "category": 3,
        "model": "fitted"
    }
},
{
    "model": "products.dress",
    "pk": 57,
    "fields": {
        "name": "The Newest",
        "description": "new dress",
        "cost": "9999",
        "color": "blue",
        "length": "mini",
        "material": "flax",
        "photo": "products_images/dress17.jpeg",
        "photo_hover": "products_images/dress17.1.jpg",
        "category": 1,
        "model": "fitted"
    }
}
]
